budget_system/__init__.py
budget_system/budget_system.py
budget_system/commandline_budget.py
budget_system/extra_types/SpentTypes.py
budget_system/extra_types/__init__.py
budget_system/parsers/__init__.py
budget_system/parsers/parsers.py
budget_system/purchase/__init__.py
budget_system/purchase/purchase.py
budget_system/settings/Config.py
budget_system/settings/DateFormat.py
budget_system/settings/DisplayStyle.py
budget_system/settings/Lang.py
budget_system/settings/LanguagesText.py
budget_system/settings/__init__.py
budget_system/settings/languages/ENG.ini
budget_system/settings/languages/FRE.ini
budget_system/settings/languages/GER.ini
budget_system/settings/languages/ITA.ini
budget_system/settings/languages/POR.ini
budget_system/settings/languages/SPA.ini
budget_system/show_data/__init__.py
budget_system/show_data/show_data.py
budget_system/spent/__init__.py
budget_system/spent/spent.py
budget_system/translation/__init__.py
budget_system/translation/translation.py
budget_system/validators/Date.py
budget_system/validators/__init__.py
budget_system/validators/months/months_by_lang.bak
budget_system/validators/months/months_by_lang.dat
budget_system/validators/months/months_by_lang.dir
budget_system-1.0.2.dist-info/LICENSE.txt
budget_system-1.0.2.dist-info/METADATA
budget_system-1.0.2.dist-info/WHEEL
budget_system-1.0.2.dist-info/entry_points.txt
budget_system-1.0.2.dist-info/top_level.txt
budget_system-1.0.2.dist-info/RECORD
