Metadata-Version: 2.1
Name: budget-system
Version: 1.0.2
Summary: Package to manage budgets for the year, month, store and date of purchase.
Home-page: https://github.com/carlosmperilla/budget-system
Author: carlosmperilla
Author-email: carlosperillaprogramacion@gmail.com
License: MIT
Keywords: spent expenses purchase budget system python package carlosmperilla
Classifier: Programming Language :: Python :: 3
Classifier: License :: OSI Approved :: MIT License
Classifier: Operating System :: OS Independent
License-File: LICENSE.txt
Requires-Dist: colorama (==0.4.4)
Requires-Dist: numpy (==1.21.6)
Requires-Dist: pandas (==1.3.5)
